pyStormworksLuaInject/__init__.py
pyStormworksLuaInject/__main__.py
pyStormworksLuaInject/pyStormworksLuaInject.egg-info/PKG-INFO
pyStormworksLuaInject/pyStormworksLuaInject.egg-info/SOURCES.txt
pyStormworksLuaInject/pyStormworksLuaInject.egg-info/dependency_links.txt
pyStormworksLuaInject/pyStormworksLuaInject.egg-info/top_level.txt
pystormworksluainject-0.1.7.dist-info/LICENSE
pystormworksluainject-0.1.7.dist-info/WHEEL
pystormworksluainject-0.1.7.dist-info/METADATA
pystormworksluainject-0.1.7.dist-info/RECORD
