Metadata-Version: 2.1
Name: pyStormworksLuaInject
Version: 0.1.7
Summary: pyStormworksLuaInject - A Python library for injecting Lua code into Stormworks Lua scripts.
Author: Trapdoor
Classifier: License :: OSI Approved :: GNU General Public License v3 or later (GPLv3+)
